quick_eks_cross_az/.DS_Store
quick_eks_cross_az/__init__.py
quick_eks_cross_az/cli.py
quick_eks_cross_az/cloudformation.yaml
quick_eks_cross_az/lib.py
quick_eks_cross_az/query.sql
quick_eks_cross_az-0.9.3.dist-info/entry_points.txt
quick_eks_cross_az-0.9.3.dist-info/LICENSE
quick_eks_cross_az-0.9.3.dist-info/WHEEL
quick_eks_cross_az-0.9.3.dist-info/METADATA
quick_eks_cross_az-0.9.3.dist-info/RECORD
