Metadata-Version: 2.1
Name: quick_eks_cross_az
Version: 0.9.3
Summary: Quick EKS corss-AZ log
Author-email: Asaf Amrmi <asaf.amrami@gmail.com>
Requires-Python: >=3.6
Classifier: Programming Language :: Python :: 3
Classifier: License :: OSI Approved :: MIT License
Classifier: Operating System :: OS Independent
Requires-Dist: PyYAML~=6.0.1
Requires-Dist: kubernetes~=29.0.0
Requires-Dist: boto3~=1.34.43
Requires-Dist: yaspin~=3.0.1
Requires-Dist: wakepy~=0.7.2
Project-URL: Bug Tracker, https://github.com/asafamr/quick-eks-cross-az/issues
Project-URL: Homepage, https://github.com/asafamr/quick-eks-cross-az
